kili_object_storage/__init__.py
kili_object_storage/constants.py
kili_object_storage/decorator.py
kili_object_storage/exceptions.py
kili_object_storage/loggings.py
kili_object_storage/object_storage.py
kili_object_storage-0.0.1.dist-info/METADATA
kili_object_storage-0.0.1.dist-info/WHEEL
kili_object_storage-0.0.1.dist-info/top_level.txt
kili_object_storage-0.0.1.dist-info/RECORD
